[{"title":"12","summary":"3321","instructions":"3213","image":"/images/12.webp","creator":"주정준","creator_email":"wnwjdwns1@gmail.com","slug":"12"},{"title":"123","summary":"123","instructions":"123","image":"/images/123.webp","creator":"123","creator_email":"wnwjdwns1@gmail.com","slug":"123"},{"title":"21","summary":"21","instructions":"21","image":"/images/21.webp","creator":"12","creator_email":"wnwjdwns1@gmail.com","slug":"21"},{"title":"12","summary":"12","instructions":"2112","image":"/images/12.webp","creator":"123","creator_email":"wnwjdwns1@gmail.com","slug":"12"},{"title":"12","summary":"21","instructions":"21","image":"/images/12.webp","creator":"주정준","creator_email":"wnwjdwns1@gmail.com","slug":"12"},{"title":"23","summary":"32","instructions":"23","image":"/images/23.webp","creator":"123","creator_email":"wnwjdwns1@gmail.com","slug":"23"}]